{
  "plan_file": "docs/plans/2026-04-06-be-w1w2w3-hookbridge-certifier.md",
  "phase": "execution",
  "created_at": "2026-04-06T15:30:00+08:00",
  "updated_at": "2026-04-06T17:00:00+08:00",
  "completed_tasks": ["W1", "W2", "W3"],
  "current_task": null,
  "total_tasks": 3,
  "phase_name": "Phase BE — EAASP 协议层 + 第二个 L1 Runtime (W1-W3)",
  "status": "W1-W3 complete. Proto refactor (common.proto extraction + hook.proto bidirectional streaming), HookBridge trait + InProcess + gRPC, eaasp-certifier contract verification tool. 54 tests total.",
  "execution_mode": "ruflo",
  "branch": "Grid",
  "baseline": {
    "tests": "54 (6 certifier + 11 hook-bridge + 24 runtime unit + 13 runtime integration)",
    "commit": "40a231e",
    "notes": "W1-W3 complete — protocol layer + HookBridge + certifier"
  },
  "tasks": {
    "W1": {
      "description": "common.proto + hook.proto + runtime.proto refactor",
      "status": "complete",
      "commit": "b5d7e54",
      "sub_tasks": {
        "T1": { "description": "Create common.proto (shared types extraction)", "status": "complete" },
        "T2": { "description": "Modify runtime.proto to import common", "status": "complete" },
        "T3": { "description": "Create hook.proto (bidirectional streaming)", "status": "complete" },
        "T4": { "description": "Update grid-runtime build.rs/lib.rs/service.rs/tests", "status": "complete" }
      }
    },
    "W2": {
      "description": "grid-hook-bridge crate (HookBridge trait + InProcess + gRPC)",
      "status": "complete",
      "commit": "c6fdb68",
      "sub_tasks": {
        "T1": { "description": "Crate skeleton + build.rs + lib.rs", "status": "complete" },
        "T2": { "description": "HookBridge trait + types (3 tests)", "status": "complete" },
        "T3": { "description": "InProcessHookBridge (8 tests)", "status": "complete" },
        "T4": { "description": "GrpcHookBridge client + HookBridgeGrpcServer", "status": "complete" }
      }
    },
    "W3": {
      "description": "eaasp-certifier contract verification tool",
      "status": "complete",
      "commit": "40a231e",
      "sub_tasks": {
        "T1": { "description": "Crate skeleton + CLI", "status": "complete" },
        "T2": { "description": "verifier.rs 16-method verification (3 tests)", "status": "complete" },
        "T3": { "description": "mock_l3.rs + report.rs (3 tests)", "status": "complete" }
      }
    }
  },
  "deferred": {
    "BE-D1": "GrpcHookBridge 端到端集成测试（需要 HookBridge server 运行）",
    "BE-D2": "certifier 端到端测试（需要 grid-runtime gRPC server 运行）",
    "BE-D3": "HookBridge 双向流集成测试",
    "BE-D4": "common.proto 到 contract.rs 类型映射自动化",
    "BE-D5": "certifier CLI mock-l3 子命令（L3 策略引擎 BH）"
  },
  "previous_phase": {
    "name": "Phase BD — grid-runtime (EAASP L1)",
    "status": "COMPLETE — 6/6 tasks @ ae4b337"
  }
}
